PriceIndices/__init__.py
PriceIndices/crypto_history.py
PriceIndices/price_indicators.py
priceindices-1.4.0.dist-info/METADATA
priceindices-1.4.0.dist-info/WHEEL
priceindices-1.4.0.dist-info/LICENSE.txt
priceindices-1.4.0.dist-info/RECORD
