Metadata-Version: 2.1
Name: priceindices
Version: 1.4.0
Summary: A python package to get historical market data of cryptocurrencies, and calculate & plot different price technical indicators.
License: MIT
Author: Dayal Chand Aichara
Author-email: dcaichara@gmail.com
Requires-Python: >=3.8,<4.0
Classifier: License :: OSI Approved :: MIT License
Classifier: Programming Language :: Python :: 3
Classifier: Programming Language :: Python :: 3.8
Classifier: Programming Language :: Python :: 3.9
Classifier: Programming Language :: Python :: 3.10
Classifier: Programming Language :: Python :: 3.11
Requires-Dist: matplotlib (>=3.6.3,<4.0.0)
Requires-Dist: numpy (>=1.24.1,<2.0.0)
Requires-Dist: pandas (>=1.4.0,<2.0.0)
Requires-Dist: requests (>=2.25.1,<3.0.0)
